LICENSE.md
README.md
pyproject.toml
setup.py
FPT_Diffusion.egg-info/PKG-INFO
FPT_Diffusion.egg-info/SOURCES.txt
FPT_Diffusion.egg-info/dependency_links.txt
FPT_Diffusion.egg-info/top_level.txt
FPTdiffusion/__init__.py
FPTdiffusion/masks.py
FPTdiffusion/mpt.py
FPTdiffusion/processing.py
FPTdiffusion/spt.py
FPTdiffusion/sptObject.py
FPTdiffusion/utils.py
tests/test.py